rtspm/__init__.py
rtspm/_spm_imatrix.py
rtspm/_spm_inv_b_cdf.py
rtspm/_spm_inv_t_cdf.py
rtspm/_spm_matrix.py
rtspm/_spm_realign_rt.py
rtspm/_spm_reslice_rt.py
rtspm/_spm_setup.py
rtspm/_spm_slice_vol.py
rtspm/_spm_smoothing.py
rtspm/errors.py
rtspm/logging.py
rtspm/version.py
_rtspm.cpython-311-x86_64-linux-gnu.so
python_rtspm-0.2.18.dist-info/LICENSE
python_rtspm-0.2.18.dist-info/METADATA
python_rtspm-0.2.18.dist-info/WHEEL
python_rtspm-0.2.18.dist-info/RECORD
