Metadata-Version: 2.3
Name: python-rtspm
Version: 0.2.18
Summary: Python adaptation of SPM functions for real-time fMRI analysis
License: GPL-3.0
Keywords: neurofeedback,neurofeedback-training,opennft,spm
Author: OpenNFT Team
Author-email: opennft@gmail.com
Requires-Python: >=3.11,<4.0
Classifier: Development Status :: 1 - Planning
Classifier: Intended Audience :: Science/Research
Classifier: License :: OSI Approved :: GNU General Public License v3 (GPLv3)
Classifier: Programming Language :: Python
Classifier: Programming Language :: Python :: 3
Classifier: Programming Language :: Python :: 3.11
Classifier: Programming Language :: Python :: 3.12
Classifier: Programming Language :: Python :: 3.13
Classifier: Programming Language :: Python :: 3 :: Only
Classifier: Programming Language :: Python :: Implementation :: CPython
Classifier: Topic :: Software Development :: Libraries
Requires-Dist: numpy (>=1.19.2)
Requires-Dist: scipy (>=1.5.4)
